{
	"schemaVersion": 1,
	"id": "fresh-armor-bar",
	"version": "${version}",
	"name": "Fresh Armor Bar",
	"description": "Replaces the vanilla armor bar with a custom texture-based HUD!",
	"authors": [
		"ZeroXXII"
	],
	"contact": {
		"sources": "https://github.com/ZeroXX11/Fresh_Armor_Bar"
	},
	"license": "MIT",
	"icon": "assets/fresh-armor-bar/icon.png",
	"environment": "client",
	"entrypoints": {
		"client": [
			"com.fresharmorbar.FreshArmorBarClient"
		]
	},
	"mixins": [
      "fresh-armor-bar.client.mixins.json"
	],
	"depends": {
		"fabricloader": ">=0.18.4",
		"minecraft": ">=1.20.1 <1.21",
		"java": ">=17",
		"fabric-api": "*"
	}
}